corgidb/__init__.py
corgidb/constants.py
corgidb/corgidb.py
corgidb/exceptions.py
corgidb/utils.py
corgidb/objects/__init__.py
corgidb/objects/condition.py
corgidb/objects/datachunk.py
corgidb/objects/table.py
corgidb-0.1.17.dist-info/LICENSE
corgidb-0.1.17.dist-info/METADATA
corgidb-0.1.17.dist-info/WHEEL
corgidb-0.1.17.dist-info/top_level.txt
corgidb-0.1.17.dist-info/RECORD
